django_stupid_storage
