Metadata-Version: 1.1
Name: djangostupidstorage
Version: 0.2.4
Summary: Simple Django WebDAV storage with upload queue.
Home-page: https://github.com/irqed/django-stupid-storage
Author: Alexander Shchepetilnikov
Author-email: alex@irqed.com
License: BSD
Download-URL: http://pypi.python.org/pypi/djangostupidstorage/
Platform: UNKNOWN
Classifier: Development Status :: 5 - Production/Stable
Classifier: Environment :: Web Environment
Classifier: Framework :: Django
Classifier: Intended Audience :: Developers
Classifier: License :: OSI Approved :: BSD License
Classifier: Operating System :: OS Independent
Classifier: Programming Language :: Python
Classifier: Topic :: Software Development :: Libraries :: Python Modules
